parallelize/__init__.py
parallelize/parallelize.py
pyparallelize-0.1.0.dist-info/METADATA
pyparallelize-0.1.0.dist-info/RECORD
pyparallelize-0.1.0.dist-info/WHEEL
pyparallelize-0.1.0.dist-info/top_level.txt
tests/__init__.py
tests/test_parallelize.py
