Metadata-Version: 2.1
Name: pyparallelize
Version: 0.1.0
Summary: Package to simplify process of parallelising tasks
Home-page: https://github.com/ismailuddin/parallelize
Author: Ismail Uddin
License: GNU
Platform: UNKNOWN
Classifier: Programming Language :: Python :: 3
Classifier: License :: OSI Approved :: GNU General Public License v3 (GPLv3)
Classifier: Operating System :: OS Independent
